.gitignore
.gitlab-ci.yml
README.md
setup.py
tox.ini
admincer/__init__.py
admincer/__main__.py
admincer/convert.py
admincer/extract.py
admincer/find.py
admincer/index.py
admincer/place.py
admincer/slice.py
admincer/util.py
admincer.egg-info/PKG-INFO
admincer.egg-info/SOURCES.txt
admincer.egg-info/dependency_links.txt
admincer.egg-info/entry_points.txt
admincer.egg-info/not-zip-safe
admincer.egg-info/requires.txt
admincer.egg-info/top_level.txt
demo/README.md
demo/run.sh
demo/banners/bs-green.png
demo/banners/bs-orange.png
demo/banners/bs-pink.png
demo/banners/bs-yellow.png
demo/banners/wi-green.png
demo/banners/wi-orange.png
demo/banners/wi-pink.png
demo/banners/wi-yellow.png
demo/labels/ad.png
demo/labels/blue-triangle.png
demo/labels/red-dot.png
demo/sides/ad-blue.png
demo/sides/ad-orange.png
demo/sides/ad-pink.png
demo/sides/ad-yellow.png
demo/sides/yay-blue.png
demo/sides/yay-orange.png
demo/sides/yay-pink.png
demo/sides/yay-yellow.png
demo/source-xcf/banners.xcf
demo/source-xcf/labels.xcf
demo/source-xcf/sides.xcf
demo/source-xcf/source-images.xcf
demo/src/1.png
demo/src/2.png
demo/src/2.txt
demo/src/index.csv
demo/src/region.names
tests/conftest.py
tests/test_cli.py
tests/test_convert.py
tests/test_extract.py
tests/test_find.py
tests/test_index.py
tests/test_place.py
tests/test_slice.py
tests/test_tests.py
tests/test_util.py
tests/data/cvat_xmls/14_task11.xml
tests/data/cvat_xmls/15_task12.xml
tests/data/logs/extract-vv.log
tests/data/logs/place-v.log
tests/data/logs/slice-v.log