Metadata-Version: 2.1
Name: admincer
Version: 1.2.0
Summary: Tool for managing datasets for visual ad detection
Home-page: https://gitlab.com/eyeo/machine-learning/admincer/
Author: eyeo GmbH
Author-email: info@adblockplus.org
License: GPLv3
Keywords: ad-detection machine-learning dataset
Platform: UNKNOWN
Classifier: Development Status :: 4 - Beta
Classifier: Intended Audience :: Developers
Classifier: License :: OSI Approved :: GNU General Public License v3 (GPLv3)
Classifier: Natural Language :: English
Classifier: Programming Language :: Python :: 3
Classifier: Operating System :: OS Independent
Classifier: Topic :: Utilities
